{
    "payload": [
        {
            "name": "Social Event",
            "created_at": "2024-05-26T12:55:11.199",
            "created_by": "Chun Mega"
        },
        {
            "name": "Social Gathering",
            "created_at": "2024-05-26T15:20:47.521",
            "created_by": "Alice Smith"
        },
        {
            "name": "Community Gathering",
            "created_at": "2024-05-27T08:10:33.874",
            "created_by": "John Doe"
        },
        {
            "name": "Networking Event",
            "created_at": "2024-05-27T16:40:22.009",
            "created_by": "Emily Jones"
        },
        {
            "name": "Social Mixer",
            "created_at": "2024-05-28T10:05:55.327",
            "created_by": "David Brown"
        },
        {
            "name": "Friendship Meetup",
            "created_at": "2024-05-28T14:30:18.650",
            "created_by": "Samantha Green"
        }
    ]
}